lhacoding/__init__.py
lhacoding/lhacoding.py
lhacoding-0.3.dist-info/METADATA
lhacoding-0.3.dist-info/WHEEL
lhacoding-0.3.dist-info/top_level.txt
lhacoding-0.3.dist-info/RECORD
